README.rst
setup.py
tests/__init__.py
tests/test_uptimerobot.py
tests/test_uptimerobot_syncable.py
urconf/__init__.py
urconf/uptimerobot.py
urconf/uptimerobot_syncable.py
urconf.egg-info/PKG-INFO
urconf.egg-info/SOURCES.txt
urconf.egg-info/dependency_links.txt
urconf.egg-info/requires.txt
urconf.egg-info/top_level.txt