Metadata-Version: 1.0
Name: urconf
Version: 2016.4
Summary: Declarative configuration library for Uptime Robot
Home-page: http://github.com/knyar/urconf
Author: Anton Tolchanov
Author-email: UNKNOWN
License: MIT
Keywords: monitoring,api,uptime robot
Platform: any
